api_gateway/__init__.py
api_gateway/api_db_utils.py
api_gateway/fast_memory_db.py
api_gateway/json_to_sqlite.py
api_gateway/server.py
iflow_mcp_cwm_api_gateway_mcp-0.1.1.dist-info/METADATA
iflow_mcp_cwm_api_gateway_mcp-0.1.1.dist-info/WHEEL
iflow_mcp_cwm_api_gateway_mcp-0.1.1.dist-info/entry_points.txt
iflow_mcp_cwm_api_gateway_mcp-0.1.1.dist-info/top_level.txt
iflow_mcp_cwm_api_gateway_mcp-0.1.1.dist-info/RECORD
