Metadata-Version: 2.4
Name: iflow-mcp_cwm-api-gateway-mcp
Version: 0.1.1
Summary: Model Context Protocol server for general API gateway to ConnectWise Manage
Author: Jason Smith
Author-email: Jason Smith <jason@example.com>
License: UNLICENSED
Project-URL: Homepage, https://github.com/iflow-mcp/cwm-api-gateway-mcp
Project-URL: Repository, https://github.com/iflow-mcp/cwm-api-gateway-mcp.git
Project-URL: Issues, https://github.com/iflow-mcp/cwm-api-gateway-mcp/issues
Classifier: Development Status :: 3 - Alpha
Classifier: Intended Audience :: Developers
Classifier: Programming Language :: Python :: 3
Classifier: Programming Language :: Python :: 3.10
Classifier: Programming Language :: Python :: 3.11
Classifier: Programming Language :: Python :: 3.12
Requires-Python: >=3.10
Requires-Dist: mcp>=1.3.0
Requires-Dist: httpx>=0.23.0
Requires-Dist: pydantic>=1.10.0
Requires-Dist: aiohttp>=3.8.4
Dynamic: author
Dynamic: requires-python
